cassini/__init__.py
cassini/accessors.py
cassini/config.py
cassini/core.py
cassini/defaults/__init__.py
cassini/defaults/templates/Home.ipynb
cassini/defaults/templates/Tier.tmplt.ipynb
cassini/defaults/tiers.py
cassini/environment.py
cassini/ext/__init__.py
cassini/ext/cassini_lib/__init__.py
cassini/ext/cassini_lib/extension.py
cassini/ext/cassini_lib/import_tools.py
cassini/ext/ipygui/__init__.py
cassini/ext/ipygui/components.py
cassini/ext/ipygui/extension.py
cassini/ext/ipygui/gui.py
cassini/jlgui.py
cassini/magics.py
cassini/meta.py
cassini/migrate/V0_2toV0_3.py
cassini/migrate/__init__.py
cassini/migrate/__main__.py
cassini/migrate/base.py
cassini/py.typed
cassini/sharing.py
cassini/testing_utils.py
cassini/utils.py
cassini-0.3.0.dist-info/LICENSE
cassini-0.3.0.dist-info/METADATA
cassini-0.3.0.dist-info/WHEEL
cassini-0.3.0.dist-info/RECORD
