Metadata-Version: 2.1
Name: cassini
Version: 0.3.0
Summary: A tool to structure experimental work, data and analysis using Jupyter Lab.
License: GPL-3.0-only
Author: 0Hughman0
Author-email: rammers2@hotmail.co.uk
Requires-Python: >=3.8.1,<4.0.0
Classifier: License :: OSI Approved :: GNU General Public License v3 (GPLv3)
Classifier: Programming Language :: Python :: 3
Classifier: Programming Language :: Python :: 3.9
Classifier: Programming Language :: Python :: 3.10
Classifier: Programming Language :: Python :: 3.11
Classifier: Programming Language :: Python :: 3.12
Classifier: Programming Language :: Python :: 3.13
Provides-Extra: cassini-lib
Provides-Extra: ipygui
Requires-Dist: ipywidgets (>=8.0,<9.0)
Requires-Dist: jupyter_cassini_server (>=0.3.0,<0.4.0)
Requires-Dist: jupyterlab (>=4.0.0,<5.0.0)
Requires-Dist: pandas (>=1.0,<2.0) ; extra == "ipygui"
Requires-Dist: pydantic (>=2.8.2,<3.0.0)
Requires-Dist: semantic-version (>=2.10.0,<3.0.0) ; extra == "cassini-lib"
Requires-Dist: typing-extensions (>=4.7.1,<5.0.0)
